[
  {
    "id": "39505417902",
    "owner": "50419993@N05",
    "title": "ANDY8701_2",
    "realname": "",
    "ownername": "TRONG VEO STUDIO - 0773083483",
    "datetaken": "2018-01-07 16:08:43",
    "max_width": 1024,
    "max_height": 683,
    "url_max": "https://live.staticflickr.com/4647/39505417902_ec8c794db9_b.jpg",
    "max_width_2000": 1024,
    "max_height_2000": 683,
    "url_max_2000": "https://live.staticflickr.com/4647/39505417902_ec8c794db9_b.jpg",
    "flickr_page": "https://www.flickr.com/photos/50419993@N05/39505417902",
    "count_view": "11279"
  },
  {
    "id": "25664467538",
    "owner": "50419993@N05",
    "title": "ANDY8670_2",
    "realname": "",
    "ownername": "TRONG VEO STUDIO - 0773083483",
    "datetaken": "2018-01-07 16:03:51",
    "max_width": 1024,
    "max_height": 683,
    "url_max": "https://live.staticflickr.com/4733/25664467538_f4412ed001_b.jpg",
    "max_width_2000": 1024,
    "max_height_2000": 683,
    "url_max_2000": "https://live.staticflickr.com/4733/25664467538_f4412ed001_b.jpg",
    "flickr_page": "https://www.flickr.com/photos/50419993@N05/25664467538",
    "count_view": "11234"
  },
  {
    "id": "38365686955",
    "owner": "50419993@N05",
    "title": "ANDY3980_2",
    "realname": "",
    "ownername": "TRONG VEO STUDIO - 0773083483",
    "datetaken": "2017-12-23 21:13:05",
    "max_width": 683,
    "max_height": 1024,
    "url_max": "https://live.staticflickr.com/4732/38365686955_5e7da4a044_b.jpg",
    "max_width_2000": 683,
    "max_height_2000": 1024,
    "url_max_2000": "https://live.staticflickr.com/4732/38365686955_5e7da4a044_b.jpg",
    "flickr_page": "https://www.flickr.com/photos/50419993@N05/38365686955",
    "count_view": "17753"
  },
  {
    "id": "24379161197",
    "owner": "50419993@N05",
    "title": "ANDY3952_2",
    "realname": "",
    "ownername": "TRONG VEO STUDIO - 0773083483",
    "datetaken": "2017-12-23 21:10:11",
    "max_width": 1024,
    "max_height": 683,
    "url_max": "https://live.staticflickr.com/4646/24379161197_92d5e60590_b.jpg",
    "max_width_2000": 1024,
    "max_height_2000": 683,
    "url_max_2000": "https://live.staticflickr.com/4646/24379161197_92d5e60590_b.jpg",
    "flickr_page": "https://www.flickr.com/photos/50419993@N05/24379161197",
    "count_view": "18125"
  },
  {
    "id": "38365311205",
    "owner": "50419993@N05",
    "title": "ANDY3949_2",
    "realname": "",
    "ownername": "TRONG VEO STUDIO - 0773083483",
    "datetaken": "2017-12-23 21:09:47",
    "max_width": 683,
    "max_height": 1024,
    "url_max": "https://live.staticflickr.com/4644/38365311205_4b03745c0f_b.jpg",
    "max_width_2000": 683,
    "max_height_2000": 1024,
    "url_max_2000": "https://live.staticflickr.com/4644/38365311205_4b03745c0f_b.jpg",
    "flickr_page": "https://www.flickr.com/photos/50419993@N05/38365311205",
    "count_view": "20168"
  },
  {
    "id": "38365323035",
    "owner": "50419993@N05",
    "title": "ANDY4188",
    "realname": "",
    "ownername": "TRONG VEO STUDIO - 0773083483",
    "datetaken": "2017-12-23 22:07:04",
    "max_width": 666,
    "max_height": 1024,
    "url_max": "https://live.staticflickr.com/4646/38365323035_5b405c13e0_b.jpg",
    "max_width_2000": 666,
    "max_height_2000": 1024,
    "url_max_2000": "https://live.staticflickr.com/4646/38365323035_5b405c13e0_b.jpg",
    "flickr_page": "https://www.flickr.com/photos/50419993@N05/38365323035",
    "count_view": "13484"
  },
  {
    "id": "38365331345",
    "owner": "50419993@N05",
    "title": "ANDY4072",
    "realname": "",
    "ownername": "TRONG VEO STUDIO - 0773083483",
    "datetaken": "2017-12-23 21:54:37",
    "max_width": 1024,
    "max_height": 683,
    "url_max": "https://live.staticflickr.com/4633/38365331345_6416242871_b.jpg",
    "max_width_2000": 1024,
    "max_height_2000": 683,
    "url_max_2000": "https://live.staticflickr.com/4633/38365331345_6416242871_b.jpg",
    "flickr_page": "https://www.flickr.com/photos/50419993@N05/38365331345",
    "count_view": "12309"
  },
  {
    "id": "27465446989",
    "owner": "50419993@N05",
    "title": "ANDY4049",
    "realname": "",
    "ownername": "TRONG VEO STUDIO - 0773083483",
    "datetaken": "2017-12-23 21:30:47",
    "max_width": 1024,
    "max_height": 683,
    "url_max": "https://live.staticflickr.com/4688/27465446989_3ae0df5757_b.jpg",
    "max_width_2000": 1024,
    "max_height_2000": 683,
    "url_max_2000": "https://live.staticflickr.com/4688/27465446989_3ae0df5757_b.jpg",
    "flickr_page": "https://www.flickr.com/photos/50419993@N05/27465446989",
    "count_view": "15901"
  },
  {
    "id": "39171504522",
    "owner": "50419993@N05",
    "title": "ANDY2967",
    "realname": "",
    "ownername": "TRONG VEO STUDIO - 0773083483",
    "datetaken": "2017-12-21 13:53:55",
    "max_width": 1024,
    "max_height": 683,
    "url_max": "https://live.staticflickr.com/4682/39171504522_a75c9fc1a0_b.jpg",
    "max_width_2000": 1024,
    "max_height_2000": 683,
    "url_max_2000": "https://live.staticflickr.com/4682/39171504522_a75c9fc1a0_b.jpg",
    "flickr_page": "https://www.flickr.com/photos/50419993@N05/39171504522",
    "count_view": "25619"
  },
  {
    "id": "39198927551",
    "owner": "50419993@N05",
    "title": "ANDY2834",
    "realname": "",
    "ownername": "TRONG VEO STUDIO - 0773083483",
    "datetaken": "2017-12-21 13:27:43",
    "max_width": 1024,
    "max_height": 683,
    "url_max": "https://live.staticflickr.com/4640/39198927551_cb1f273f4c_b.jpg",
    "max_width_2000": 1024,
    "max_height_2000": 683,
    "url_max_2000": "https://live.staticflickr.com/4640/39198927551_cb1f273f4c_b.jpg",
    "flickr_page": "https://www.flickr.com/photos/50419993@N05/39198927551",
    "count_view": "28930"
  },
  {
    "id": "25333528278",
    "owner": "50419993@N05",
    "title": "ANDY2781",
    "realname": "",
    "ownername": "TRONG VEO STUDIO - 0773083483",
    "datetaken": "2017-12-21 13:20:53",
    "max_width": 1024,
    "max_height": 683,
    "url_max": "https://live.staticflickr.com/4684/25333528278_12e41a909a_b.jpg",
    "max_width_2000": 1024,
    "max_height_2000": 683,
    "url_max_2000": "https://live.staticflickr.com/4684/25333528278_12e41a909a_b.jpg",
    "flickr_page": "https://www.flickr.com/photos/50419993@N05/25333528278",
    "count_view": "18790"
  },
  {
    "id": "39171519372",
    "owner": "50419993@N05",
    "title": "ANDY2719",
    "realname": "",
    "ownername": "TRONG VEO STUDIO - 0773083483",
    "datetaken": "2017-12-21 13:11:53",
    "max_width": 651,
    "max_height": 1024,
    "url_max": "https://live.staticflickr.com/4736/39171519372_6342e54016_b.jpg",
    "max_width_2000": 651,
    "max_height_2000": 1024,
    "url_max_2000": "https://live.staticflickr.com/4736/39171519372_6342e54016_b.jpg",
    "flickr_page": "https://www.flickr.com/photos/50419993@N05/39171519372",
    "count_view": "22044"
  },
  {
    "id": "39171523422",
    "owner": "50419993@N05",
    "title": "ANDY2487",
    "realname": "",
    "ownername": "TRONG VEO STUDIO - 0773083483",
    "datetaken": "2017-12-21 12:30:44",
    "max_width": 1024,
    "max_height": 683,
    "url_max": "https://live.staticflickr.com/4599/39171523422_64874b0370_b.jpg",
    "max_width_2000": 1024,
    "max_height_2000": 683,
    "url_max_2000": "https://live.staticflickr.com/4599/39171523422_64874b0370_b.jpg",
    "flickr_page": "https://www.flickr.com/photos/50419993@N05/39171523422",
    "count_view": "24575"
  },
  {
    "id": "24275146007",
    "owner": "50419993@N05",
    "title": "ANDY2022_2",
    "realname": "",
    "ownername": "TRONG VEO STUDIO - 0773083483",
    "datetaken": "2017-12-18 15:37:22",
    "max_width": 1024,
    "max_height": 683,
    "url_max": "https://live.staticflickr.com/4734/24275146007_78fbdcc395_b.jpg",
    "max_width_2000": 1024,
    "max_height_2000": 683,
    "url_max_2000": "https://live.staticflickr.com/4734/24275146007_78fbdcc395_b.jpg",
    "flickr_page": "https://www.flickr.com/photos/50419993@N05/24275146007",
    "count_view": "14804"
  },
  {
    "id": "25268374528",
    "owner": "50419993@N05",
    "title": "ANDY1949",
    "realname": "",
    "ownername": "TRONG VEO STUDIO - 0773083483",
    "datetaken": "2017-12-18 15:21:03",
    "max_width": 1024,
    "max_height": 683,
    "url_max": "https://live.staticflickr.com/4596/25268374528_1650fd6b59_b.jpg",
    "max_width_2000": 1024,
    "max_height_2000": 683,
    "url_max_2000": "https://live.staticflickr.com/4596/25268374528_1650fd6b59_b.jpg",
    "flickr_page": "https://www.flickr.com/photos/50419993@N05/25268374528",
    "count_view": "15209"
  },
  {
    "id": "27357427819",
    "owner": "50419993@N05",
    "title": "ANDY1869_2",
    "realname": "",
    "ownername": "TRONG VEO STUDIO - 0773083483",
    "datetaken": "2017-12-18 15:01:54",
    "max_width": 683,
    "max_height": 1024,
    "url_max": "https://live.staticflickr.com/4734/27357427819_d6e1ab0237_b.jpg",
    "max_width_2000": 683,
    "max_height_2000": 1024,
    "url_max_2000": "https://live.staticflickr.com/4734/27357427819_d6e1ab0237_b.jpg",
    "flickr_page": "https://www.flickr.com/photos/50419993@N05/27357427819",
    "count_view": "13783"
  },
  {
    "id": "24275166667",
    "owner": "50419993@N05",
    "title": "ANDY1833_2",
    "realname": "",
    "ownername": "TRONG VEO STUDIO - 0773083483",
    "datetaken": "2017-12-18 14:53:02",
    "max_width": 1024,
    "max_height": 683,
    "url_max": "https://live.staticflickr.com/4644/24275166667_f919876cee_b.jpg",
    "max_width_2000": 1024,
    "max_height_2000": 683,
    "url_max_2000": "https://live.staticflickr.com/4644/24275166667_f919876cee_b.jpg",
    "flickr_page": "https://www.flickr.com/photos/50419993@N05/24275166667",
    "count_view": "14092"
  },
  {
    "id": "25268377248",
    "owner": "50419993@N05",
    "title": "ANDY1827",
    "realname": "",
    "ownername": "TRONG VEO STUDIO - 0773083483",
    "datetaken": "2017-12-18 14:52:33",
    "max_width": 1024,
    "max_height": 683,
    "url_max": "https://live.staticflickr.com/4738/25268377248_78abc36e1a_b.jpg",
    "max_width_2000": 1024,
    "max_height_2000": 683,
    "url_max_2000": "https://live.staticflickr.com/4738/25268377248_78abc36e1a_b.jpg",
    "flickr_page": "https://www.flickr.com/photos/50419993@N05/25268377248",
    "count_view": "16076"
  },
  {
    "id": "25268396448",
    "owner": "50419993@N05",
    "title": "ANDY1810",
    "realname": "",
    "ownername": "TRONG VEO STUDIO - 0773083483",
    "datetaken": "2017-12-18 14:48:37",
    "max_width": 683,
    "max_height": 1024,
    "url_max": "https://live.staticflickr.com/4596/25268396448_4e8cfa4252_b.jpg",
    "max_width_2000": 683,
    "max_height_2000": 1024,
    "url_max_2000": "https://live.staticflickr.com/4596/25268396448_4e8cfa4252_b.jpg",
    "flickr_page": "https://www.flickr.com/photos/50419993@N05/25268396448",
    "count_view": "17008"
  },
  {
    "id": "38217764504",
    "owner": "50419993@N05",
    "title": "ANDY9767",
    "realname": "",
    "ownername": "TRONG VEO STUDIO - 0773083483",
    "datetaken": "2017-12-09 12:00:21",
    "max_width": 1024,
    "max_height": 683,
    "url_max": "https://live.staticflickr.com/4684/38217764504_2743f4636e_b.jpg",
    "max_width_2000": 1024,
    "max_height_2000": 683,
    "url_max_2000": "https://live.staticflickr.com/4684/38217764504_2743f4636e_b.jpg",
    "flickr_page": "https://www.flickr.com/photos/50419993@N05/38217764504",
    "count_view": "22504"
  },
  {
    "id": "38217768494",
    "owner": "50419993@N05",
    "title": "ANDY9728",
    "realname": "",
    "ownername": "TRONG VEO STUDIO - 0773083483",
    "datetaken": "2017-12-09 12:00:34",
    "max_width": 683,
    "max_height": 1024,
    "url_max": "https://live.staticflickr.com/4524/38217768494_1ff2dd439c_b.jpg",
    "max_width_2000": 683,
    "max_height_2000": 1024,
    "url_max_2000": "https://live.staticflickr.com/4524/38217768494_1ff2dd439c_b.jpg",
    "flickr_page": "https://www.flickr.com/photos/50419993@N05/38217768494",
    "count_view": "18553"
  },
  {
    "id": "38217770634",
    "owner": "50419993@N05",
    "title": "ANDY9662",
    "realname": "",
    "ownername": "TRONG VEO STUDIO - 0773083483",
    "datetaken": "2017-12-09 12:01:40",
    "max_width": 1024,
    "max_height": 683,
    "url_max": "https://live.staticflickr.com/4687/38217770634_948f8d7c67_b.jpg",
    "max_width_2000": 1024,
    "max_height_2000": 683,
    "url_max_2000": "https://live.staticflickr.com/4687/38217770634_948f8d7c67_b.jpg",
    "flickr_page": "https://www.flickr.com/photos/50419993@N05/38217770634",
    "count_view": "32314"
  },
  {
    "id": "38111756774",
    "owner": "50419993@N05",
    "title": "3",
    "realname": "",
    "ownername": "TRONG VEO STUDIO - 0773083483",
    "datetaken": "2017-12-04 10:54:58",
    "max_width": 683,
    "max_height": 1024,
    "url_max": "https://live.staticflickr.com/4553/38111756774_b4d2fc9521_b.jpg",
    "max_width_2000": 683,
    "max_height_2000": 1024,
    "url_max_2000": "https://live.staticflickr.com/4553/38111756774_b4d2fc9521_b.jpg",
    "flickr_page": "https://www.flickr.com/photos/50419993@N05/38111756774",
    "count_view": "21451"
  },
  {
    "id": "38111746714",
    "owner": "50419993@N05",
    "title": "ANDY9050",
    "realname": "",
    "ownername": "TRONG VEO STUDIO - 0773083483",
    "datetaken": "2017-12-04 10:42:54",
    "max_width": 1024,
    "max_height": 683,
    "url_max": "https://live.staticflickr.com/4555/38111746714_d5f4ffd970_b.jpg",
    "max_width_2000": 1024,
    "max_height_2000": 683,
    "url_max_2000": "https://live.staticflickr.com/4555/38111746714_d5f4ffd970_b.jpg",
    "flickr_page": "https://www.flickr.com/photos/50419993@N05/38111746714",
    "count_view": "16680"
  },
  {
    "id": "38111743124",
    "owner": "50419993@N05",
    "title": "ANDY9054",
    "realname": "",
    "ownername": "TRONG VEO STUDIO - 0773083483",
    "datetaken": "2017-12-04 10:56:29",
    "max_width": 683,
    "max_height": 1024,
    "url_max": "https://live.staticflickr.com/4576/38111743124_7e25edd752_b.jpg",
    "max_width_2000": 683,
    "max_height_2000": 1024,
    "url_max_2000": "https://live.staticflickr.com/4576/38111743124_7e25edd752_b.jpg",
    "flickr_page": "https://www.flickr.com/photos/50419993@N05/38111743124",
    "count_view": "17114"
  },
  {
    "id": "38825553201",
    "owner": "50419993@N05",
    "title": "ANDY9063",
    "realname": "",
    "ownername": "TRONG VEO STUDIO - 0773083483",
    "datetaken": "2017-12-04 08:19:55",
    "max_width": 683,
    "max_height": 1024,
    "url_max": "https://live.staticflickr.com/4543/38825553201_56e0ac9239_b.jpg",
    "max_width_2000": 683,
    "max_height_2000": 1024,
    "url_max_2000": "https://live.staticflickr.com/4543/38825553201_56e0ac9239_b.jpg",
    "flickr_page": "https://www.flickr.com/photos/50419993@N05/38825553201",
    "count_view": "17591"
  },
  {
    "id": "38790973462",
    "owner": "50419993@N05",
    "title": "ANDY8602",
    "realname": "",
    "ownername": "TRONG VEO STUDIO - 0773083483",
    "datetaken": "2017-12-04 03:44:15",
    "max_width": 683,
    "max_height": 1024,
    "url_max": "https://live.staticflickr.com/4567/38790973462_bde7d47241_b.jpg",
    "max_width_2000": 683,
    "max_height_2000": 1024,
    "url_max_2000": "https://live.staticflickr.com/4567/38790973462_bde7d47241_b.jpg",
    "flickr_page": "https://www.flickr.com/photos/50419993@N05/38790973462",
    "count_view": "18903"
  },
  {
    "id": "23957232867",
    "owner": "50419993@N05",
    "title": "ANDY8643",
    "realname": "",
    "ownername": "TRONG VEO STUDIO - 0773083483",
    "datetaken": "2017-12-04 03:22:50",
    "max_width": 1024,
    "max_height": 683,
    "url_max": "https://live.staticflickr.com/4574/23957232867_df31b8ef05_b.jpg",
    "max_width_2000": 1024,
    "max_height_2000": 683,
    "url_max_2000": "https://live.staticflickr.com/4574/23957232867_df31b8ef05_b.jpg",
    "flickr_page": "https://www.flickr.com/photos/50419993@N05/23957232867",
    "count_view": "18786"
  },
  {
    "id": "27028111659",
    "owner": "50419993@N05",
    "title": "ANDY8765",
    "realname": "",
    "ownername": "TRONG VEO STUDIO - 0773083483",
    "datetaken": "2017-12-03 10:25:06",
    "max_width": 1024,
    "max_height": 683,
    "url_max": "https://live.staticflickr.com/4580/27028111659_0d61845b5b_b.jpg",
    "max_width_2000": 1024,
    "max_height_2000": 683,
    "url_max_2000": "https://live.staticflickr.com/4580/27028111659_0d61845b5b_b.jpg",
    "flickr_page": "https://www.flickr.com/photos/50419993@N05/27028111659",
    "count_view": "20694"
  },
  {
    "id": "38803124001",
    "owner": "50419993@N05",
    "title": "ANDY8829",
    "realname": "",
    "ownername": "TRONG VEO STUDIO - 0773083483",
    "datetaken": "2017-12-03 09:33:39",
    "max_width": 683,
    "max_height": 1024,
    "url_max": "https://live.staticflickr.com/4579/38803124001_b593a374f5_b.jpg",
    "max_width_2000": 683,
    "max_height_2000": 1024,
    "url_max_2000": "https://live.staticflickr.com/4579/38803124001_b593a374f5_b.jpg",
    "flickr_page": "https://www.flickr.com/photos/50419993@N05/38803124001",
    "count_view": "23839"
  },
  {
    "id": "24931024758",
    "owner": "50419993@N05",
    "title": "ANDY8579",
    "realname": "",
    "ownername": "TRONG VEO STUDIO - 0773083483",
    "datetaken": "2017-12-03 09:54:30",
    "max_width": 1024,
    "max_height": 683,
    "url_max": "https://live.staticflickr.com/4561/24931024758_2389a750b1_b.jpg",
    "max_width_2000": 1024,
    "max_height_2000": 683,
    "url_max_2000": "https://live.staticflickr.com/4561/24931024758_2389a750b1_b.jpg",
    "flickr_page": "https://www.flickr.com/photos/50419993@N05/24931024758",
    "count_view": "21599"
  },
  {
    "id": "27028113569",
    "owner": "50419993@N05",
    "title": "ANDY8656-2",
    "realname": "",
    "ownername": "TRONG VEO STUDIO - 0773083483",
    "datetaken": "2017-12-03 09:44:47",
    "max_width": 683,
    "max_height": 1024,
    "url_max": "https://live.staticflickr.com/4524/27028113569_18cb632c3d_b.jpg",
    "max_width_2000": 683,
    "max_height_2000": 1024,
    "url_max_2000": "https://live.staticflickr.com/4524/27028113569_18cb632c3d_b.jpg",
    "flickr_page": "https://www.flickr.com/photos/50419993@N05/27028113569",
    "count_view": "20908"
  },
  {
    "id": "27028106789",
    "owner": "50419993@N05",
    "title": "ANDY8865",
    "realname": "",
    "ownername": "TRONG VEO STUDIO - 0773083483",
    "datetaken": "2017-12-03 10:08:50",
    "max_width": 683,
    "max_height": 1024,
    "url_max": "https://live.staticflickr.com/4540/27028106789_fc5410cc81_b.jpg",
    "max_width_2000": 683,
    "max_height_2000": 1024,
    "url_max_2000": "https://live.staticflickr.com/4540/27028106789_fc5410cc81_b.jpg",
    "flickr_page": "https://www.flickr.com/photos/50419993@N05/27028106789",
    "count_view": "15814"
  },
  {
    "id": "38070780684",
    "owner": "50419993@N05",
    "title": "633A6000",
    "realname": "",
    "ownername": "TRONG VEO STUDIO - 0773083483",
    "datetaken": "2017-12-02 16:14:20",
    "max_width": 1024,
    "max_height": 683,
    "url_max": "https://live.staticflickr.com/4556/38070780684_c8ae40d947_b.jpg",
    "max_width_2000": 1024,
    "max_height_2000": 683,
    "url_max_2000": "https://live.staticflickr.com/4556/38070780684_c8ae40d947_b.jpg",
    "flickr_page": "https://www.flickr.com/photos/50419993@N05/38070780684",
    "count_view": "19248"
  },
  {
    "id": "38756338542",
    "owner": "50419993@N05",
    "title": "633A6247",
    "realname": "",
    "ownername": "TRONG VEO STUDIO - 0773083483",
    "datetaken": "2017-12-02 15:55:19",
    "max_width": 683,
    "max_height": 1024,
    "url_max": "https://live.staticflickr.com/4530/38756338542_d705df517e_b.jpg",
    "max_width_2000": 683,
    "max_height_2000": 1024,
    "url_max_2000": "https://live.staticflickr.com/4530/38756338542_d705df517e_b.jpg",
    "flickr_page": "https://www.flickr.com/photos/50419993@N05/38756338542",
    "count_view": "21354"
  },
  {
    "id": "27011528599",
    "owner": "50419993@N05",
    "title": "633A6053",
    "realname": "",
    "ownername": "TRONG VEO STUDIO - 0773083483",
    "datetaken": "2017-12-02 15:39:21",
    "max_width": 1024,
    "max_height": 683,
    "url_max": "https://live.staticflickr.com/4551/27011528599_13e5d66baa_b.jpg",
    "max_width_2000": 1024,
    "max_height_2000": 683,
    "url_max_2000": "https://live.staticflickr.com/4551/27011528599_13e5d66baa_b.jpg",
    "flickr_page": "https://www.flickr.com/photos/50419993@N05/27011528599",
    "count_view": "29378"
  },
  {
    "id": "38695228741",
    "owner": "50419993@N05",
    "title": "ANDY7051",
    "realname": "",
    "ownername": "TRONG VEO STUDIO - 0773083483",
    "datetaken": "2017-11-28 13:42:39",
    "max_width": 683,
    "max_height": 1024,
    "url_max": "https://live.staticflickr.com/4564/38695228741_1f2971fafc_b.jpg",
    "max_width_2000": 683,
    "max_height_2000": 1024,
    "url_max_2000": "https://live.staticflickr.com/4564/38695228741_1f2971fafc_b.jpg",
    "flickr_page": "https://www.flickr.com/photos/50419993@N05/38695228741",
    "count_view": "23679"
  },
  {
    "id": "37976826394",
    "owner": "50419993@N05",
    "title": "ANDY6954",
    "realname": "",
    "ownername": "TRONG VEO STUDIO - 0773083483",
    "datetaken": "2017-11-28 07:06:18",
    "max_width": 683,
    "max_height": 1024,
    "url_max": "https://live.staticflickr.com/4555/37976826394_2608cee490_b.jpg",
    "max_width_2000": 683,
    "max_height_2000": 1024,
    "url_max_2000": "https://live.staticflickr.com/4555/37976826394_2608cee490_b.jpg",
    "flickr_page": "https://www.flickr.com/photos/50419993@N05/37976826394",
    "count_view": "20560"
  },
  {
    "id": "38695229961",
    "owner": "50419993@N05",
    "title": "ANDY6918",
    "realname": "",
    "ownername": "TRONG VEO STUDIO - 0773083483",
    "datetaken": "2017-11-28 06:47:51",
    "max_width": 1024,
    "max_height": 683,
    "url_max": "https://live.staticflickr.com/4552/38695229961_ec601ed022_b.jpg",
    "max_width_2000": 1024,
    "max_height_2000": 683,
    "url_max_2000": "https://live.staticflickr.com/4552/38695229961_ec601ed022_b.jpg",
    "flickr_page": "https://www.flickr.com/photos/50419993@N05/38695229961",
    "count_view": "22253"
  },
  {
    "id": "37976827794",
    "owner": "50419993@N05",
    "title": "ANDY6836",
    "realname": "",
    "ownername": "TRONG VEO STUDIO - 0773083483",
    "datetaken": "2017-11-28 06:52:36",
    "max_width": 1024,
    "max_height": 683,
    "url_max": "https://live.staticflickr.com/4545/37976827794_9861a89a05_b.jpg",
    "max_width_2000": 1024,
    "max_height_2000": 683,
    "url_max_2000": "https://live.staticflickr.com/4545/37976827794_9861a89a05_b.jpg",
    "flickr_page": "https://www.flickr.com/photos/50419993@N05/37976827794",
    "count_view": "15019"
  },
  {
    "id": "38695232881",
    "owner": "50419993@N05",
    "title": "ANDY6793",
    "realname": "",
    "ownername": "TRONG VEO STUDIO - 0773083483",
    "datetaken": "2017-11-28 14:02:03",
    "max_width": 683,
    "max_height": 1024,
    "url_max": "https://live.staticflickr.com/4583/38695232881_3474114fba_b.jpg",
    "max_width_2000": 683,
    "max_height_2000": 1024,
    "url_max_2000": "https://live.staticflickr.com/4583/38695232881_3474114fba_b.jpg",
    "flickr_page": "https://www.flickr.com/photos/50419993@N05/38695232881",
    "count_view": "15860"
  },
  {
    "id": "38616482316",
    "owner": "50419993@N05",
    "title": "ANDY6779",
    "realname": "",
    "ownername": "TRONG VEO STUDIO - 0773083483",
    "datetaken": "2017-11-27 06:47:07",
    "max_width": 1024,
    "max_height": 683,
    "url_max": "https://live.staticflickr.com/4574/38616482316_9d541cb7fd_b.jpg",
    "max_width_2000": 1024,
    "max_height_2000": 683,
    "url_max_2000": "https://live.staticflickr.com/4574/38616482316_9d541cb7fd_b.jpg",
    "flickr_page": "https://www.flickr.com/photos/50419993@N05/38616482316",
    "count_view": "22775"
  },
  {
    "id": "37954830664",
    "owner": "50419993@N05",
    "title": "ANDY7003",
    "realname": "",
    "ownername": "TRONG VEO STUDIO - 0773083483",
    "datetaken": "2017-11-27 14:09:15",
    "max_width": 593,
    "max_height": 1024,
    "url_max": "https://live.staticflickr.com/4545/37954830664_f656ca303f_b.jpg",
    "max_width_2000": 593,
    "max_height_2000": 1024,
    "url_max_2000": "https://live.staticflickr.com/4545/37954830664_f656ca303f_b.jpg",
    "flickr_page": "https://www.flickr.com/photos/50419993@N05/37954830664",
    "count_view": "21794"
  },
  {
    "id": "26880370079",
    "owner": "50419993@N05",
    "title": "ANDY7043",
    "realname": "",
    "ownername": "TRONG VEO STUDIO - 0773083483",
    "datetaken": "2017-11-26 15:27:25",
    "max_width": 1024,
    "max_height": 730,
    "url_max": "https://live.staticflickr.com/4565/26880370079_e4c031cf60_b.jpg",
    "max_width_2000": 1024,
    "max_height_2000": 730,
    "url_max_2000": "https://live.staticflickr.com/4565/26880370079_e4c031cf60_b.jpg",
    "flickr_page": "https://www.flickr.com/photos/50419993@N05/26880370079",
    "count_view": "31464"
  },
  {
    "id": "38623548972",
    "owner": "50419993@N05",
    "title": "ANDY6949",
    "realname": "",
    "ownername": "TRONG VEO STUDIO - 0773083483",
    "datetaken": "2017-11-26 14:25:48",
    "max_width": 683,
    "max_height": 1024,
    "url_max": "https://live.staticflickr.com/4569/38623548972_b3f57bcffa_b.jpg",
    "max_width_2000": 683,
    "max_height_2000": 1024,
    "url_max_2000": "https://live.staticflickr.com/4569/38623548972_b3f57bcffa_b.jpg",
    "flickr_page": "https://www.flickr.com/photos/50419993@N05/38623548972",
    "count_view": "19856"
  },
  {
    "id": "37768094635",
    "owner": "50419993@N05",
    "title": "ANDY6829",
    "realname": "",
    "ownername": "TRONG VEO STUDIO - 0773083483",
    "datetaken": "2017-11-26 14:25:29",
    "max_width": 1024,
    "max_height": 683,
    "url_max": "https://live.staticflickr.com/4530/37768094635_5e8a06cf1a_b.jpg",
    "max_width_2000": 1024,
    "max_height_2000": 683,
    "url_max_2000": "https://live.staticflickr.com/4530/37768094635_5e8a06cf1a_b.jpg",
    "flickr_page": "https://www.flickr.com/photos/50419993@N05/37768094635",
    "count_view": "21308"
  },
  {
    "id": "38599621326",
    "owner": "50419993@N05",
    "title": "ANDY6798",
    "realname": "",
    "ownername": "TRONG VEO STUDIO - 0773083483",
    "datetaken": "2017-11-26 14:36:03",
    "max_width": 1024,
    "max_height": 683,
    "url_max": "https://live.staticflickr.com/4523/38599621326_8178747d32_b.jpg",
    "max_width_2000": 1024,
    "max_height_2000": 683,
    "url_max_2000": "https://live.staticflickr.com/4523/38599621326_8178747d32_b.jpg",
    "flickr_page": "https://www.flickr.com/photos/50419993@N05/38599621326",
    "count_view": "17798"
  },
  {
    "id": "26614866999",
    "owner": "50419993@N05",
    "title": "ANDY5197",
    "realname": "",
    "ownername": "TRONG VEO STUDIO - 0773083483",
    "datetaken": "2017-11-13 14:48:39",
    "max_width": 1024,
    "max_height": 683,
    "url_max": "https://live.staticflickr.com/4581/26614866999_a0cfcf5d28_b.jpg",
    "max_width_2000": 1024,
    "max_height_2000": 683,
    "url_max_2000": "https://live.staticflickr.com/4581/26614866999_a0cfcf5d28_b.jpg",
    "flickr_page": "https://www.flickr.com/photos/50419993@N05/26614866999",
    "count_view": "16995"
  },
  {
    "id": "38380521631",
    "owner": "50419993@N05",
    "title": "IMG_2282",
    "realname": "",
    "ownername": "TRONG VEO STUDIO - 0773083483",
    "datetaken": "2017-11-12 13:33:51",
    "max_width": 1024,
    "max_height": 683,
    "url_max": "https://live.staticflickr.com/4581/38380521631_b05e34a0a9_b.jpg",
    "max_width_2000": 1024,
    "max_height_2000": 683,
    "url_max_2000": "https://live.staticflickr.com/4581/38380521631_b05e34a0a9_b.jpg",
    "flickr_page": "https://www.flickr.com/photos/50419993@N05/38380521631",
    "count_view": "16857"
  },
  {
    "id": "26604858159",
    "owner": "50419993@N05",
    "title": "IMG_2272",
    "realname": "",
    "ownername": "TRONG VEO STUDIO - 0773083483",
    "datetaken": "2017-11-13 04:58:06",
    "max_width": 1024,
    "max_height": 683,
    "url_max": "https://live.staticflickr.com/4568/26604858159_fc075afa26_b.jpg",
    "max_width_2000": 1024,
    "max_height_2000": 683,
    "url_max_2000": "https://live.staticflickr.com/4568/26604858159_fc075afa26_b.jpg",
    "flickr_page": "https://www.flickr.com/photos/50419993@N05/26604858159",
    "count_view": "14900"
  },
  {
    "id": "38325597326",
    "owner": "50419993@N05",
    "title": "IMG_2265",
    "realname": "",
    "ownername": "TRONG VEO STUDIO - 0773083483",
    "datetaken": "2017-11-12 13:34:25",
    "max_width": 683,
    "max_height": 1024,
    "url_max": "https://live.staticflickr.com/4568/38325597326_39111b1e44_b.jpg",
    "max_width_2000": 683,
    "max_height_2000": 1024,
    "url_max_2000": "https://live.staticflickr.com/4568/38325597326_39111b1e44_b.jpg",
    "flickr_page": "https://www.flickr.com/photos/50419993@N05/38325597326",
    "count_view": "14014"
  },
  {
    "id": "24510104808",
    "owner": "50419993@N05",
    "title": "IMG_2182",
    "realname": "",
    "ownername": "TRONG VEO STUDIO - 0773083483",
    "datetaken": "2017-11-13 05:05:03",
    "max_width": 683,
    "max_height": 1024,
    "url_max": "https://live.staticflickr.com/4570/24510104808_a8c2db4d32_b.jpg",
    "max_width_2000": 683,
    "max_height_2000": 1024,
    "url_max_2000": "https://live.staticflickr.com/4570/24510104808_a8c2db4d32_b.jpg",
    "flickr_page": "https://www.flickr.com/photos/50419993@N05/24510104808",
    "count_view": "15235"
  },
  {
    "id": "38325631936",
    "owner": "50419993@N05",
    "title": "IMG_2115",
    "realname": "",
    "ownername": "TRONG VEO STUDIO - 0773083483",
    "datetaken": "2017-11-13 05:11:26",
    "max_width": 683,
    "max_height": 1024,
    "url_max": "https://live.staticflickr.com/4517/38325631936_dd83678e97_b.jpg",
    "max_width_2000": 683,
    "max_height_2000": 1024,
    "url_max_2000": "https://live.staticflickr.com/4517/38325631936_dd83678e97_b.jpg",
    "flickr_page": "https://www.flickr.com/photos/50419993@N05/38325631936",
    "count_view": "13561"
  },
  {
    "id": "24510151068",
    "owner": "50419993@N05",
    "title": "ANDY5254",
    "realname": "",
    "ownername": "TRONG VEO STUDIO - 0773083483",
    "datetaken": "2017-11-13 04:38:20",
    "max_width": 683,
    "max_height": 1024,
    "url_max": "https://live.staticflickr.com/4543/24510151068_6d5ba7724b_b.jpg",
    "max_width_2000": 683,
    "max_height_2000": 1024,
    "url_max_2000": "https://live.staticflickr.com/4543/24510151068_6d5ba7724b_b.jpg",
    "flickr_page": "https://www.flickr.com/photos/50419993@N05/24510151068",
    "count_view": "14916"
  },
  {
    "id": "38350267152",
    "owner": "50419993@N05",
    "title": "ANDY5176",
    "realname": "",
    "ownername": "TRONG VEO STUDIO - 0773083483",
    "datetaken": "2017-11-12 13:38:29",
    "max_width": 1024,
    "max_height": 683,
    "url_max": "https://live.staticflickr.com/4585/38350267152_c42a49a36b_b.jpg",
    "max_width_2000": 1024,
    "max_height_2000": 683,
    "url_max_2000": "https://live.staticflickr.com/4585/38350267152_c42a49a36b_b.jpg",
    "flickr_page": "https://www.flickr.com/photos/50419993@N05/38350267152",
    "count_view": "14006"
  },
  {
    "id": "24510202168",
    "owner": "50419993@N05",
    "title": "ANDY5082",
    "realname": "",
    "ownername": "TRONG VEO STUDIO - 0773083483",
    "datetaken": "2017-11-13 05:20:35",
    "max_width": 1024,
    "max_height": 683,
    "url_max": "https://live.staticflickr.com/4575/24510202168_6e1f9e4a9f_b.jpg",
    "max_width_2000": 1024,
    "max_height_2000": 683,
    "url_max_2000": "https://live.staticflickr.com/4575/24510202168_6e1f9e4a9f_b.jpg",
    "flickr_page": "https://www.flickr.com/photos/50419993@N05/24510202168",
    "count_view": "13418"
  },
  {
    "id": "38358294151",
    "owner": "50419993@N05",
    "title": "ANDY5075",
    "realname": "",
    "ownername": "TRONG VEO STUDIO - 0773083483",
    "datetaken": "2017-11-12 12:21:02",
    "max_width": 1024,
    "max_height": 683,
    "url_max": "https://live.staticflickr.com/4526/38358294151_b0a9279657_b.jpg",
    "max_width_2000": 1024,
    "max_height_2000": 683,
    "url_max_2000": "https://live.staticflickr.com/4526/38358294151_b0a9279657_b.jpg",
    "flickr_page": "https://www.flickr.com/photos/50419993@N05/38358294151",
    "count_view": "15186"
  },
  {
    "id": "26583033979",
    "owner": "50419993@N05",
    "title": "IMG_2121",
    "realname": "",
    "ownername": "TRONG VEO STUDIO - 0773083483",
    "datetaken": "2017-11-12 12:33:30",
    "max_width": 683,
    "max_height": 1024,
    "url_max": "https://live.staticflickr.com/4547/26583033979_310edda478_b.jpg",
    "max_width_2000": 683,
    "max_height_2000": 1024,
    "url_max_2000": "https://live.staticflickr.com/4547/26583033979_310edda478_b.jpg",
    "flickr_page": "https://www.flickr.com/photos/50419993@N05/26583033979",
    "count_view": "14633"
  },
  {
    "id": "37644140254",
    "owner": "50419993@N05",
    "title": "ANDY5064",
    "realname": "",
    "ownername": "TRONG VEO STUDIO - 0773083483",
    "datetaken": "2017-11-12 12:07:17",
    "max_width": 683,
    "max_height": 1024,
    "url_max": "https://live.staticflickr.com/4516/37644140254_228fac80be_b.jpg",
    "max_width_2000": 683,
    "max_height_2000": 1024,
    "url_max_2000": "https://live.staticflickr.com/4516/37644140254_228fac80be_b.jpg",
    "flickr_page": "https://www.flickr.com/photos/50419993@N05/37644140254",
    "count_view": "16979"
  },
  {
    "id": "37328904691",
    "owner": "50419993@N05",
    "title": "DSC03814",
    "realname": "",
    "ownername": "TRONG VEO STUDIO - 0773083483",
    "datetaken": "2017-09-26 17:38:28",
    "max_width": 1024,
    "max_height": 683,
    "url_max": "https://live.staticflickr.com/4393/37328904691_1d51fce072_b.jpg",
    "max_width_2000": 1024,
    "max_height_2000": 683,
    "url_max_2000": "https://live.staticflickr.com/4393/37328904691_1d51fce072_b.jpg",
    "flickr_page": "https://www.flickr.com/photos/50419993@N05/37328904691",
    "count_view": "16398"
  },
  {
    "id": "37328906331",
    "owner": "50419993@N05",
    "title": "DSC03736",
    "realname": "",
    "ownername": "TRONG VEO STUDIO - 0773083483",
    "datetaken": "2017-09-26 17:38:35",
    "max_width": 1024,
    "max_height": 683,
    "url_max": "https://live.staticflickr.com/4331/37328906331_dc9aa597bb_b.jpg",
    "max_width_2000": 1024,
    "max_height_2000": 683,
    "url_max_2000": "https://live.staticflickr.com/4331/37328906331_dc9aa597bb_b.jpg",
    "flickr_page": "https://www.flickr.com/photos/50419993@N05/37328906331",
    "count_view": "16466"
  },
  {
    "id": "37298886982",
    "owner": "50419993@N05",
    "title": "DSC03727",
    "realname": "",
    "ownername": "TRONG VEO STUDIO - 0773083483",
    "datetaken": "2017-09-26 17:38:38",
    "max_width": 1024,
    "max_height": 683,
    "url_max": "https://live.staticflickr.com/4404/37298886982_8930c29cca_b.jpg",
    "max_width_2000": 1024,
    "max_height_2000": 683,
    "url_max_2000": "https://live.staticflickr.com/4404/37298886982_8930c29cca_b.jpg",
    "flickr_page": "https://www.flickr.com/photos/50419993@N05/37298886982",
    "count_view": "15898"
  },
  {
    "id": "37328911701",
    "owner": "50419993@N05",
    "title": "DSC03666",
    "realname": "",
    "ownername": "TRONG VEO STUDIO - 0773083483",
    "datetaken": "2017-09-26 17:38:32",
    "max_width": 1024,
    "max_height": 683,
    "url_max": "https://live.staticflickr.com/4480/37328911701_7719de5e87_b.jpg",
    "max_width_2000": 1024,
    "max_height_2000": 683,
    "url_max_2000": "https://live.staticflickr.com/4480/37328911701_7719de5e87_b.jpg",
    "flickr_page": "https://www.flickr.com/photos/50419993@N05/37328911701",
    "count_view": "14179"
  },
  {
    "id": "37072623300",
    "owner": "50419993@N05",
    "title": "DSC03579",
    "realname": "",
    "ownername": "TRONG VEO STUDIO - 0773083483",
    "datetaken": "2017-09-26 17:38:41",
    "max_width": 1024,
    "max_height": 683,
    "url_max": "https://live.staticflickr.com/4347/37072623300_fb8a09e195_b.jpg",
    "max_width_2000": 1024,
    "max_height_2000": 683,
    "url_max_2000": "https://live.staticflickr.com/4347/37072623300_fb8a09e195_b.jpg",
    "flickr_page": "https://www.flickr.com/photos/50419993@N05/37072623300",
    "count_view": "13476"
  },
  {
    "id": "37281942366",
    "owner": "50419993@N05",
    "title": "633A8155",
    "realname": "",
    "ownername": "TRONG VEO STUDIO - 0773083483",
    "datetaken": "2017-09-26 13:38:37",
    "max_width": 683,
    "max_height": 1024,
    "url_max": "https://live.staticflickr.com/4477/37281942366_a488d8d14a_b.jpg",
    "max_width_2000": 683,
    "max_height_2000": 1024,
    "url_max_2000": "https://live.staticflickr.com/4477/37281942366_a488d8d14a_b.jpg",
    "flickr_page": "https://www.flickr.com/photos/50419993@N05/37281942366",
    "count_view": "12546"
  },
  {
    "id": "37328911111",
    "owner": "50419993@N05",
    "title": "633A8108",
    "realname": "",
    "ownername": "TRONG VEO STUDIO - 0773083483",
    "datetaken": "2017-09-26 13:38:30",
    "max_width": 1024,
    "max_height": 683,
    "url_max": "https://live.staticflickr.com/4347/37328911111_7421dbcb1c_b.jpg",
    "max_width_2000": 1024,
    "max_height_2000": 683,
    "url_max_2000": "https://live.staticflickr.com/4347/37328911111_7421dbcb1c_b.jpg",
    "flickr_page": "https://www.flickr.com/photos/50419993@N05/37328911111",
    "count_view": "12425"
  },
  {
    "id": "37281944836",
    "owner": "50419993@N05",
    "title": "633A8092",
    "realname": "",
    "ownername": "TRONG VEO STUDIO - 0773083483",
    "datetaken": "2017-09-26 13:38:23",
    "max_width": 1024,
    "max_height": 683,
    "url_max": "https://live.staticflickr.com/4478/37281944836_71fb10acdb_b.jpg",
    "max_width_2000": 1024,
    "max_height_2000": 683,
    "url_max_2000": "https://live.staticflickr.com/4478/37281944836_71fb10acdb_b.jpg",
    "flickr_page": "https://www.flickr.com/photos/50419993@N05/37281944836",
    "count_view": "12169"
  },
  {
    "id": "37298887702",
    "owner": "50419993@N05",
    "title": "633A8200",
    "realname": "",
    "ownername": "TRONG VEO STUDIO - 0773083483",
    "datetaken": "2017-09-25 15:41:04",
    "max_width": 1024,
    "max_height": 683,
    "url_max": "https://live.staticflickr.com/4372/37298887702_89ca5f7fca_b.jpg",
    "max_width_2000": 1024,
    "max_height_2000": 683,
    "url_max_2000": "https://live.staticflickr.com/4372/37298887702_89ca5f7fca_b.jpg",
    "flickr_page": "https://www.flickr.com/photos/50419993@N05/37298887702",
    "count_view": "11932"
  },
  {
    "id": "37072623830",
    "owner": "50419993@N05",
    "title": "633A8188",
    "realname": "",
    "ownername": "TRONG VEO STUDIO - 0773083483",
    "datetaken": "2017-09-25 15:41:01",
    "max_width": 1024,
    "max_height": 683,
    "url_max": "https://live.staticflickr.com/4464/37072623830_1fdc1538ae_b.jpg",
    "max_width_2000": 1024,
    "max_height_2000": 683,
    "url_max_2000": "https://live.staticflickr.com/4464/37072623830_1fdc1538ae_b.jpg",
    "flickr_page": "https://www.flickr.com/photos/50419993@N05/37072623830",
    "count_view": "11846"
  },
  {
    "id": "37072625070",
    "owner": "50419993@N05",
    "title": "633A8160",
    "realname": "",
    "ownername": "TRONG VEO STUDIO - 0773083483",
    "datetaken": "2017-09-25 15:40:58",
    "max_width": 1024,
    "max_height": 683,
    "url_max": "https://live.staticflickr.com/4340/37072625070_18380e3046_b.jpg",
    "max_width_2000": 1024,
    "max_height_2000": 683,
    "url_max_2000": "https://live.staticflickr.com/4340/37072625070_18380e3046_b.jpg",
    "flickr_page": "https://www.flickr.com/photos/50419993@N05/37072625070",
    "count_view": "12048"
  },
  {
    "id": "37328908211",
    "owner": "50419993@N05",
    "title": "633A8085",
    "realname": "",
    "ownername": "TRONG VEO STUDIO - 0773083483",
    "datetaken": "2017-09-25 15:38:48",
    "max_width": 1024,
    "max_height": 683,
    "url_max": "https://live.staticflickr.com/4476/37328908211_4091f12479_b.jpg",
    "max_width_2000": 1024,
    "max_height_2000": 683,
    "url_max_2000": "https://live.staticflickr.com/4476/37328908211_4091f12479_b.jpg",
    "flickr_page": "https://www.flickr.com/photos/50419993@N05/37328908211",
    "count_view": "11521"
  },
  {
    "id": "37328918501",
    "owner": "50419993@N05",
    "title": "633A8052",
    "realname": "",
    "ownername": "TRONG VEO STUDIO - 0773083483",
    "datetaken": "2017-09-25 15:41:09",
    "max_width": 1024,
    "max_height": 683,
    "url_max": "https://live.staticflickr.com/4395/37328918501_6f201f19a2_b.jpg",
    "max_width_2000": 1024,
    "max_height_2000": 683,
    "url_max_2000": "https://live.staticflickr.com/4395/37328918501_6f201f19a2_b.jpg",
    "flickr_page": "https://www.flickr.com/photos/50419993@N05/37328918501",
    "count_view": "11779"
  },
  {
    "id": "36578572634",
    "owner": "50419993@N05",
    "title": "633A8201-2",
    "realname": "",
    "ownername": "TRONG VEO STUDIO - 0773083483",
    "datetaken": "2017-09-24 22:15:49",
    "max_width": 1024,
    "max_height": 683,
    "url_max": "https://live.staticflickr.com/4487/36578572634_ffb4418f63_b.jpg",
    "max_width_2000": 1024,
    "max_height_2000": 683,
    "url_max_2000": "https://live.staticflickr.com/4487/36578572634_ffb4418f63_b.jpg",
    "flickr_page": "https://www.flickr.com/photos/50419993@N05/36578572634",
    "count_view": "13312"
  },
  {
    "id": "37288505991",
    "owner": "50419993@N05",
    "title": "633A8155-2",
    "realname": "",
    "ownername": "TRONG VEO STUDIO - 0773083483",
    "datetaken": "2017-09-24 22:15:53",
    "max_width": 683,
    "max_height": 1024,
    "url_max": "https://live.staticflickr.com/4399/37288505991_6326e88247_b.jpg",
    "max_width_2000": 683,
    "max_height_2000": 1024,
    "url_max_2000": "https://live.staticflickr.com/4399/37288505991_6326e88247_b.jpg",
    "flickr_page": "https://www.flickr.com/photos/50419993@N05/37288505991",
    "count_view": "12705"
  },
  {
    "id": "37241634976",
    "owner": "50419993@N05",
    "title": "633A8104-2",
    "realname": "",
    "ownername": "TRONG VEO STUDIO - 0773083483",
    "datetaken": "2017-09-24 22:15:51",
    "max_width": 1024,
    "max_height": 683,
    "url_max": "https://live.staticflickr.com/4372/37241634976_d743de436f_b.jpg",
    "max_width_2000": 1024,
    "max_height_2000": 683,
    "url_max_2000": "https://live.staticflickr.com/4372/37241634976_d743de436f_b.jpg",
    "flickr_page": "https://www.flickr.com/photos/50419993@N05/37241634976",
    "count_view": "13099"
  },
  {
    "id": "53538747706",
    "owner": "50419993@N05",
    "title": "NguyenTuyetNhung1681",
    "realname": "",
    "ownername": "TRONG VEO STUDIO - 0773083483",
    "datetaken": "2024-02-18 04:11:10",
    "max_width": 663,
    "max_height": 1024,
    "url_max": "https://live.staticflickr.com/65535/53538747706_7bfaa91393_b.jpg",
    "max_width_2000": 663,
    "max_height_2000": 1024,
    "url_max_2000": "https://live.staticflickr.com/65535/53538747706_7bfaa91393_b.jpg",
    "flickr_page": "https://www.flickr.com/photos/50419993@N05/53538747706",
    "count_view": "13016"
  },
  {
    "id": "53537869677",
    "owner": "50419993@N05",
    "title": "NguyenTuyetNhung1668",
    "realname": "",
    "ownername": "TRONG VEO STUDIO - 0773083483",
    "datetaken": "2024-02-18 04:11:13",
    "max_width": 664,
    "max_height": 1024,
    "url_max": "https://live.staticflickr.com/65535/53537869677_0330c0f7e9_b.jpg",
    "max_width_2000": 664,
    "max_height_2000": 1024,
    "url_max_2000": "https://live.staticflickr.com/65535/53537869677_0330c0f7e9_b.jpg",
    "flickr_page": "https://www.flickr.com/photos/50419993@N05/53537869677",
    "count_view": "26700"
  },
  {
    "id": "53535484159",
    "owner": "50419993@N05",
    "title": "Lilly6105",
    "realname": "",
    "ownername": "TRONG VEO STUDIO - 0773083483",
    "datetaken": "2023-07-13 12:49:46",
    "max_width": 1024,
    "max_height": 683,
    "url_max": "https://live.staticflickr.com/65535/53535484159_c68d6351d3_b.jpg",
    "max_width_2000": 1024,
    "max_height_2000": 683,
    "url_max_2000": "https://live.staticflickr.com/65535/53535484159_c68d6351d3_b.jpg",
    "flickr_page": "https://www.flickr.com/photos/50419993@N05/53535484159",
    "count_view": "10929"
  },
  {
    "id": "53535484189",
    "owner": "50419993@N05",
    "title": "Lilly6078",
    "realname": "",
    "ownername": "TRONG VEO STUDIO - 0773083483",
    "datetaken": "2023-07-13 12:47:23",
    "max_width": 683,
    "max_height": 1024,
    "url_max": "https://live.staticflickr.com/65535/53535484189_83d4db55ed_b.jpg",
    "max_width_2000": 683,
    "max_height_2000": 1024,
    "url_max_2000": "https://live.staticflickr.com/65535/53535484189_83d4db55ed_b.jpg",
    "flickr_page": "https://www.flickr.com/photos/50419993@N05/53535484189",
    "count_view": "11599"
  },
  {
    "id": "53535348783",
    "owner": "50419993@N05",
    "title": "Lilly6063",
    "realname": "",
    "ownername": "TRONG VEO STUDIO - 0773083483",
    "datetaken": "2023-07-13 12:46:00",
    "max_width": 1024,
    "max_height": 683,
    "url_max": "https://live.staticflickr.com/65535/53535348783_0b858e26b3_b.jpg",
    "max_width_2000": 1024,
    "max_height_2000": 683,
    "url_max_2000": "https://live.staticflickr.com/65535/53535348783_0b858e26b3_b.jpg",
    "flickr_page": "https://www.flickr.com/photos/50419993@N05/53535348783",
    "count_view": "12457"
  },
  {
    "id": "53534283847",
    "owner": "50419993@N05",
    "title": "Lilly6027",
    "realname": "",
    "ownername": "TRONG VEO STUDIO - 0773083483",
    "datetaken": "2023-07-13 12:44:00",
    "max_width": 683,
    "max_height": 1024,
    "url_max": "https://live.staticflickr.com/65535/53534283847_411e56417d_b.jpg",
    "max_width_2000": 683,
    "max_height_2000": 1024,
    "url_max_2000": "https://live.staticflickr.com/65535/53534283847_411e56417d_b.jpg",
    "flickr_page": "https://www.flickr.com/photos/50419993@N05/53534283847",
    "count_view": "8242"
  },
  {
    "id": "53535168556",
    "owner": "50419993@N05",
    "title": "Lilly6013",
    "realname": "",
    "ownername": "TRONG VEO STUDIO - 0773083483",
    "datetaken": "2023-07-13 12:43:24",
    "max_width": 683,
    "max_height": 1024,
    "url_max": "https://live.staticflickr.com/65535/53535168556_0266243ba1_b.jpg",
    "max_width_2000": 683,
    "max_height_2000": 1024,
    "url_max_2000": "https://live.staticflickr.com/65535/53535168556_0266243ba1_b.jpg",
    "flickr_page": "https://www.flickr.com/photos/50419993@N05/53535168556",
    "count_view": "5648"
  },
  {
    "id": "53535484454",
    "owner": "50419993@N05",
    "title": "Lilly6006",
    "realname": "",
    "ownername": "TRONG VEO STUDIO - 0773083483",
    "datetaken": "2023-07-13 12:43:04",
    "max_width": 1024,
    "max_height": 683,
    "url_max": "https://live.staticflickr.com/65535/53535484454_8ec6b978db_b.jpg",
    "max_width_2000": 1024,
    "max_height_2000": 683,
    "url_max_2000": "https://live.staticflickr.com/65535/53535484454_8ec6b978db_b.jpg",
    "flickr_page": "https://www.flickr.com/photos/50419993@N05/53535484454",
    "count_view": "5504"
  },
  {
    "id": "53535484499",
    "owner": "50419993@N05",
    "title": "Lilly6001",
    "realname": "",
    "ownername": "TRONG VEO STUDIO - 0773083483",
    "datetaken": "2023-07-13 12:40:55",
    "max_width": 1024,
    "max_height": 683,
    "url_max": "https://live.staticflickr.com/65535/53535484499_8a7a5ca97c_b.jpg",
    "max_width_2000": 1024,
    "max_height_2000": 683,
    "url_max_2000": "https://live.staticflickr.com/65535/53535484499_8a7a5ca97c_b.jpg",
    "flickr_page": "https://www.flickr.com/photos/50419993@N05/53535484499",
    "count_view": "6115"
  },
  {
    "id": "53535349128",
    "owner": "50419993@N05",
    "title": "Lilly5986",
    "realname": "",
    "ownername": "TRONG VEO STUDIO - 0773083483",
    "datetaken": "2023-07-13 12:40:28",
    "max_width": 683,
    "max_height": 1024,
    "url_max": "https://live.staticflickr.com/65535/53535349128_d841caf5e4_b.jpg",
    "max_width_2000": 683,
    "max_height_2000": 1024,
    "url_max_2000": "https://live.staticflickr.com/65535/53535349128_d841caf5e4_b.jpg",
    "flickr_page": "https://www.flickr.com/photos/50419993@N05/53535349128",
    "count_view": "5675"
  },
  {
    "id": "53535349333",
    "owner": "50419993@N05",
    "title": "Lilly5969",
    "realname": "",
    "ownername": "TRONG VEO STUDIO - 0773083483",
    "datetaken": "2023-07-13 12:39:03",
    "max_width": 1024,
    "max_height": 683,
    "url_max": "https://live.staticflickr.com/65535/53535349333_5b4daa7aa7_b.jpg",
    "max_width_2000": 1024,
    "max_height_2000": 683,
    "url_max_2000": "https://live.staticflickr.com/65535/53535349333_5b4daa7aa7_b.jpg",
    "flickr_page": "https://www.flickr.com/photos/50419993@N05/53535349333",
    "count_view": "5594"
  },
  {
    "id": "53535349413",
    "owner": "50419993@N05",
    "title": "Lilly5952",
    "realname": "",
    "ownername": "TRONG VEO STUDIO - 0773083483",
    "datetaken": "2023-07-13 12:37:41",
    "max_width": 1024,
    "max_height": 683,
    "url_max": "https://live.staticflickr.com/65535/53535349413_74357f2fbd_b.jpg",
    "max_width_2000": 1024,
    "max_height_2000": 683,
    "url_max_2000": "https://live.staticflickr.com/65535/53535349413_74357f2fbd_b.jpg",
    "flickr_page": "https://www.flickr.com/photos/50419993@N05/53535349413",
    "count_view": "5794"
  },
  {
    "id": "53535168961",
    "owner": "50419993@N05",
    "title": "Lilly5938",
    "realname": "",
    "ownername": "TRONG VEO STUDIO - 0773083483",
    "datetaken": "2023-07-13 12:35:12",
    "max_width": 1024,
    "max_height": 683,
    "url_max": "https://live.staticflickr.com/65535/53535168961_7c686ceb8a_b.jpg",
    "max_width_2000": 1024,
    "max_height_2000": 683,
    "url_max_2000": "https://live.staticflickr.com/65535/53535168961_7c686ceb8a_b.jpg",
    "flickr_page": "https://www.flickr.com/photos/50419993@N05/53535168961",
    "count_view": "5344"
  },
  {
    "id": "53535168846",
    "owner": "50419993@N05",
    "title": "Lilly5856",
    "realname": "",
    "ownername": "TRONG VEO STUDIO - 0773083483",
    "datetaken": "2023-07-13 12:29:49",
    "max_width": 1024,
    "max_height": 683,
    "url_max": "https://live.staticflickr.com/65535/53535168846_e8b0115d07_b.jpg",
    "max_width_2000": 1024,
    "max_height_2000": 683,
    "url_max_2000": "https://live.staticflickr.com/65535/53535168846_e8b0115d07_b.jpg",
    "flickr_page": "https://www.flickr.com/photos/50419993@N05/53535168846",
    "count_view": "4984"
  },
  {
    "id": "53535349578",
    "owner": "50419993@N05",
    "title": "Lilly5843",
    "realname": "",
    "ownername": "TRONG VEO STUDIO - 0773083483",
    "datetaken": "2023-07-13 12:29:11",
    "max_width": 1024,
    "max_height": 683,
    "url_max": "https://live.staticflickr.com/65535/53535349578_fb542af44c_b.jpg",
    "max_width_2000": 1024,
    "max_height_2000": 683,
    "url_max_2000": "https://live.staticflickr.com/65535/53535349578_fb542af44c_b.jpg",
    "flickr_page": "https://www.flickr.com/photos/50419993@N05/53535349578",
    "count_view": "4504"
  },
  {
    "id": "53535349678",
    "owner": "50419993@N05",
    "title": "Lilly5842",
    "realname": "",
    "ownername": "TRONG VEO STUDIO - 0773083483",
    "datetaken": "2023-07-13 12:29:06",
    "max_width": 1024,
    "max_height": 683,
    "url_max": "https://live.staticflickr.com/65535/53535349678_07b3dd3ca2_b.jpg",
    "max_width_2000": 1024,
    "max_height_2000": 683,
    "url_max_2000": "https://live.staticflickr.com/65535/53535349678_07b3dd3ca2_b.jpg",
    "flickr_page": "https://www.flickr.com/photos/50419993@N05/53535349678",
    "count_view": "4680"
  },
  {
    "id": "53535349898",
    "owner": "50419993@N05",
    "title": "Lilly5825",
    "realname": "",
    "ownername": "TRONG VEO STUDIO - 0773083483",
    "datetaken": "2023-07-13 12:27:15",
    "max_width": 682,
    "max_height": 1024,
    "url_max": "https://live.staticflickr.com/65535/53535349898_180712c7f6_b.jpg",
    "max_width_2000": 682,
    "max_height_2000": 1024,
    "url_max_2000": "https://live.staticflickr.com/65535/53535349898_180712c7f6_b.jpg",
    "flickr_page": "https://www.flickr.com/photos/50419993@N05/53535349898",
    "count_view": "4689"
  },
  {
    "id": "53535169256",
    "owner": "50419993@N05",
    "title": "Lilly5818",
    "realname": "",
    "ownername": "TRONG VEO STUDIO - 0773083483",
    "datetaken": "2023-07-13 12:26:52",
    "max_width": 1024,
    "max_height": 683,
    "url_max": "https://live.staticflickr.com/65535/53535169256_7624d5c56a_b.jpg",
    "max_width_2000": 1024,
    "max_height_2000": 683,
    "url_max_2000": "https://live.staticflickr.com/65535/53535169256_7624d5c56a_b.jpg",
    "flickr_page": "https://www.flickr.com/photos/50419993@N05/53535169256",
    "count_view": "4467"
  },
  {
    "id": "53535485274",
    "owner": "50419993@N05",
    "title": "Lilly5785",
    "realname": "",
    "ownername": "TRONG VEO STUDIO - 0773083483",
    "datetaken": "2023-07-13 12:24:36",
    "max_width": 1024,
    "max_height": 683,
    "url_max": "https://live.staticflickr.com/65535/53535485274_3538a0eb0c_b.jpg",
    "max_width_2000": 1024,
    "max_height_2000": 683,
    "url_max_2000": "https://live.staticflickr.com/65535/53535485274_3538a0eb0c_b.jpg",
    "flickr_page": "https://www.flickr.com/photos/50419993@N05/53535485274",
    "count_view": "4966"
  },
  {
    "id": "53534284927",
    "owner": "50419993@N05",
    "title": "Lilly5736",
    "realname": "",
    "ownername": "TRONG VEO STUDIO - 0773083483",
    "datetaken": "2023-07-13 12:20:42",
    "max_width": 1024,
    "max_height": 683,
    "url_max": "https://live.staticflickr.com/65535/53534284927_b05cca3320_b.jpg",
    "max_width_2000": 1024,
    "max_height_2000": 683,
    "url_max_2000": "https://live.staticflickr.com/65535/53534284927_b05cca3320_b.jpg",
    "flickr_page": "https://www.flickr.com/photos/50419993@N05/53534284927",
    "count_view": "4382"
  },
  {
    "id": "53535591025",
    "owner": "50419993@N05",
    "title": "Lilly5688",
    "realname": "",
    "ownername": "TRONG VEO STUDIO - 0773083483",
    "datetaken": "2023-07-13 12:17:38",
    "max_width": 682,
    "max_height": 1024,
    "url_max": "https://live.staticflickr.com/65535/53535591025_975683d5d3_b.jpg",
    "max_width_2000": 682,
    "max_height_2000": 1024,
    "url_max_2000": "https://live.staticflickr.com/65535/53535591025_975683d5d3_b.jpg",
    "flickr_page": "https://www.flickr.com/photos/50419993@N05/53535591025",
    "count_view": "4382"
  },
  {
    "id": "53535350578",
    "owner": "50419993@N05",
    "title": "Lilly5592",
    "realname": "",
    "ownername": "TRONG VEO STUDIO - 0773083483",
    "datetaken": "2023-07-13 12:11:25",
    "max_width": 1024,
    "max_height": 683,
    "url_max": "https://live.staticflickr.com/65535/53535350578_e49d7acee0_b.jpg",
    "max_width_2000": 1024,
    "max_height_2000": 683,
    "url_max_2000": "https://live.staticflickr.com/65535/53535350578_e49d7acee0_b.jpg",
    "flickr_page": "https://www.flickr.com/photos/50419993@N05/53535350578",
    "count_view": "4706"
  },
  {
    "id": "53535485694",
    "owner": "50419993@N05",
    "title": "Lilly5528",
    "realname": "",
    "ownername": "TRONG VEO STUDIO - 0773083483",
    "datetaken": "2023-07-13 12:07:18",
    "max_width": 1024,
    "max_height": 683,
    "url_max": "https://live.staticflickr.com/65535/53535485694_5db739e88e_b.jpg",
    "max_width_2000": 1024,
    "max_height_2000": 683,
    "url_max_2000": "https://live.staticflickr.com/65535/53535485694_5db739e88e_b.jpg",
    "flickr_page": "https://www.flickr.com/photos/50419993@N05/53535485694",
    "count_view": "4807"
  },
  {
    "id": "53535485809",
    "owner": "50419993@N05",
    "title": "Lilly5509",
    "realname": "",
    "ownername": "TRONG VEO STUDIO - 0773083483",
    "datetaken": "2023-07-13 12:05:04",
    "max_width": 683,
    "max_height": 1024,
    "url_max": "https://live.staticflickr.com/65535/53535485809_2622e7592f_b.jpg",
    "max_width_2000": 683,
    "max_height_2000": 1024,
    "url_max_2000": "https://live.staticflickr.com/65535/53535485809_2622e7592f_b.jpg",
    "flickr_page": "https://www.flickr.com/photos/50419993@N05/53535485809",
    "count_view": "4523"
  },
  {
    "id": "53535485869",
    "owner": "50419993@N05",
    "title": "Lilly5476",
    "realname": "",
    "ownername": "TRONG VEO STUDIO - 0773083483",
    "datetaken": "2023-07-13 12:02:06",
    "max_width": 683,
    "max_height": 1024,
    "url_max": "https://live.staticflickr.com/65535/53535485869_7f000af5f5_b.jpg",
    "max_width_2000": 683,
    "max_height_2000": 1024,
    "url_max_2000": "https://live.staticflickr.com/65535/53535485869_7f000af5f5_b.jpg",
    "flickr_page": "https://www.flickr.com/photos/50419993@N05/53535485869",
    "count_view": "4651"
  }
]